klaviyo_sdk_beta/__init__.py
klaviyo_sdk_beta/custom_retry.py
klaviyo_sdk_beta/wrapper.py
openapi_client/__init__.py
openapi_client/api_client.py
openapi_client/configuration.py
openapi_client/exceptions.py
openapi_client/model_utils.py
openapi_client/rest.py
openapi_client/api/__init__.py
openapi_client/api/catalogs_api.py
openapi_client/api/client_api.py
openapi_client/api/events_api.py
openapi_client/api/flows_api.py
openapi_client/api/lists_api.py
openapi_client/api/metrics_api.py
openapi_client/api/profiles_api.py
openapi_client/api/segments_api.py
openapi_client/api/templates_api.py
openapi_client/apis/__init__.py
openapi_client/model/__init__.py
openapi_client/model/catalog_category_create_job_create_query.py
openapi_client/model/catalog_category_create_job_create_query_as_sub_resource.py
openapi_client/model/catalog_category_create_job_create_query_as_sub_resource_attributes.py
openapi_client/model/catalog_category_create_query.py
openapi_client/model/catalog_category_create_query_as_sub_resource.py
openapi_client/model/catalog_category_create_query_as_sub_resource_attributes.py
openapi_client/model/catalog_category_delete_job_create_query.py
openapi_client/model/catalog_category_delete_job_create_query_as_sub_resource.py
openapi_client/model/catalog_category_delete_job_create_query_as_sub_resource_attributes.py
openapi_client/model/catalog_category_delete_query_as_sub_resource.py
openapi_client/model/catalog_category_item_op.py
openapi_client/model/catalog_category_update_job_create_query.py
openapi_client/model/catalog_category_update_job_create_query_as_sub_resource.py
openapi_client/model/catalog_category_update_job_create_query_as_sub_resource_attributes.py
openapi_client/model/catalog_category_update_query.py
openapi_client/model/catalog_category_update_query_as_sub_resource.py
openapi_client/model/catalog_category_update_query_as_sub_resource_attributes.py
openapi_client/model/catalog_item_category_op.py
klaviyo_sdk_beta-1.0.3.20220907.dist-info/LICENSE
klaviyo_sdk_beta-1.0.3.20220907.dist-info/METADATA
klaviyo_sdk_beta-1.0.3.20220907.dist-info/WHEEL
klaviyo_sdk_beta-1.0.3.20220907.dist-info/top_level.txt
klaviyo_sdk_beta-1.0.3.20220907.dist-info/RECORD
