Metadata-Version: 2.1
Name: klaviyo-sdk-beta
Version: 1.0.3.20220907
Summary: Klaviyo Python SDK Beta
Home-page: https://github.com/klaviyo/klaviyo-python-sdk-beta
Author: Klaviyo Developers
Author-email: developers@klaviyo.com
Project-URL: API Docs, https://developers.klaviyo.com/
Classifier: Programming Language :: Python :: 3
Classifier: License :: OSI Approved :: MIT License
Classifier: Operating System :: OS Independent
Requires-Python: >=3.6
License-File: LICENSE
Requires-Dist: certifi (>=14.05.14)
Requires-Dist: six (>=1.10)
Requires-Dist: python-dateutil (>=2.5.3)
Requires-Dist: setuptools (>=21.0.0)
Requires-Dist: urllib3 (>=1.15.1)
Requires-Dist: tenacity (>=8.0.0)
Requires-Dist: requests (>=2.26.0)
